acolytes/__init__.py
acolytes/__main__.py
acolytes/cli.py
acolytes/commands/__init__.py
acolytes/commands/backup_command.py
acolytes/commands/clean_command.py
acolytes/commands/doctor_command.py
acolytes/commands/init_command.py
acolytes/commands/list_command.py
acolytes/commands/repair_command.py
acolytes/commands/update_command.py
acolytes/data/agents/analyst.data.md
acolytes/data/agents/analyst.strategic.md
acolytes/data/agents/audit.compliance.md
acolytes/data/agents/audit.security.md
acolytes/data/agents/backend.api.md
acolytes/data/agents/backend.go.md
acolytes/data/agents/backend.java.md
acolytes/data/agents/backend.laravel.md
acolytes/data/agents/backend.nodejs.md
acolytes/data/agents/backend.python.md
acolytes/data/agents/backend.rust.md
acolytes/data/agents/backend.serverless.md
acolytes/data/agents/business.billing.md
acolytes/data/agents/business.payment.md
acolytes/data/agents/business.subscription.md
acolytes/data/agents/coordinator.backend.md
acolytes/data/agents/coordinator.database.md
acolytes/data/agents/coordinator.devops.md
acolytes/data/agents/coordinator.frontend.md
acolytes/data/agents/coordinator.infrastructure.md
acolytes/data/agents/coordinator.migration.md
acolytes/data/agents/coordinator.security.md
acolytes/data/agents/coordinator.testing.md
acolytes/data/agents/database.mariadb.md
acolytes/data/agents/database.mongodb.md
acolytes/data/agents/database.pgvector.md
acolytes/data/agents/database.postgis.md
acolytes/data/agents/database.postgres.md
acolytes/data/agents/database.redis.md
acolytes/data/agents/database.sqlite.md
acolytes/data/agents/database.timescale.md
acolytes/data/agents/database.vectorial.md
acolytes/data/agents/docs.specialist.md
acolytes/data/agents/frontend.angular.md
acolytes/data/agents/frontend.mobile.md
acolytes/data/agents/frontend.react.md
acolytes/data/agents/frontend.vue.md
acolytes/data/agents/ops.bash.md
acolytes/data/agents/ops.cicd.md
acolytes/data/agents/ops.containers.md
acolytes/data/agents/ops.git.md
acolytes-2.1.2.dist-info/licenses/LICENSE
acolytes-2.1.2.dist-info/METADATA
acolytes-2.1.2.dist-info/WHEEL
acolytes-2.1.2.dist-info/entry_points.txt
acolytes-2.1.2.dist-info/top_level.txt
acolytes-2.1.2.dist-info/RECORD
