Metadata-Version: 2.4
Name: acolytes
Version: 2.1.2
Summary: Acolytes for Claude Code - Multi-agent system with 57+ specialized AI assistants
Home-page: https://github.com/unmasSk/acolytes
Author: unmasSk
Author-email: 
Maintainer: unmasSk
License: MIT
Project-URL: Homepage, https://github.com/unmasSk/acolytes
Project-URL: Repository, https://github.com/unmasSk/acolytes
Project-URL: Issues, https://github.com/unmasSk/acolytes/issues
Keywords: claude,ai,agents,automation,development,assistant
Classifier: Development Status :: 4 - Beta
Classifier: Intended Audience :: Developers
Classifier: License :: OSI Approved :: MIT License
Classifier: Programming Language :: Python :: 3
Classifier: Programming Language :: Python :: 3.8
Classifier: Programming Language :: Python :: 3.9
Classifier: Programming Language :: Python :: 3.10
Classifier: Programming Language :: Python :: 3.11
Classifier: Programming Language :: Python :: 3.12
Classifier: Operating System :: OS Independent
Classifier: Topic :: Software Development :: Libraries :: Python Modules
Requires-Python: >=3.8
License-File: LICENSE
Requires-Dist: click>=8.0
Requires-Dist: requests>=2.28
Requires-Dist: colorama>=0.4
Requires-Dist: packaging>=21.0
Requires-Dist: tqdm>=4.67.1
Requires-Dist: setuptools>=75.3.2
Dynamic: home-page
Dynamic: license-file
Dynamic: requires-python
